README.md
setup.py
x_py_libs/__init__.py
x_py_libs.egg-info/PKG-INFO
x_py_libs.egg-info/SOURCES.txt
x_py_libs.egg-info/dependency_links.txt
x_py_libs.egg-info/requires.txt
x_py_libs.egg-info/top_level.txt
x_py_libs/db/__init__.py
x_py_libs/db/db_helper_base.py
x_py_libs/db/db_helper_mssql.py
x_py_libs/db/db_helper_mysql.py
x_py_libs/db/db_helper_pg.py
x_py_libs/extensions/__init__.py
x_py_libs/extensions/base_handler_tornado.py
x_py_libs/helpers/__init__.py
x_py_libs/helpers/app_redis_helper.py
x_py_libs/helpers/captcha_helper.py
x_py_libs/helpers/crypto_helper.py
x_py_libs/helpers/download_helper.py
x_py_libs/helpers/flask_helper.py
x_py_libs/helpers/icache_helper.py
x_py_libs/helpers/io_helper.py
x_py_libs/helpers/model_transfer_helper.py
x_py_libs/helpers/redis_helper.py
x_py_libs/helpers/requests_helper.py
x_py_libs/helpers/utilities_helper.py
x_py_libs/libs/__init__.py
x_py_libs/libs/pkcs7.py
x_py_libs/libs/typed.py