Metadata-Version: 1.0
Name: x-py-libs
Version: 0.5.20
Summary: self python libs
Home-page: https://github.com/xiaxiazhu119
Author: xiaxiazhu
Author-email: xiaxiazhu147@gmail.com
License: MIT Licence
Keywords: pip,self,python,libs
Platform: any
